.gitignore
LICENSE
MANIFEST.in
README.md
setup.py
svetlyak40wt/__init__.py
svetlyak40wt.recipe.symlinks.egg-info/PKG-INFO
svetlyak40wt.recipe.symlinks.egg-info/SOURCES.txt
svetlyak40wt.recipe.symlinks.egg-info/dependency_links.txt
svetlyak40wt.recipe.symlinks.egg-info/entry_points.txt
svetlyak40wt.recipe.symlinks.egg-info/namespace_packages.txt
svetlyak40wt.recipe.symlinks.egg-info/not-zip-safe
svetlyak40wt.recipe.symlinks.egg-info/requires.txt
svetlyak40wt.recipe.symlinks.egg-info/top_level.txt
svetlyak40wt/recipe/__init__.py
svetlyak40wt/recipe/symlinks.py