Metadata-Version: 1.0
Name: svetlyak40wt.recipe.symlinks
Version: 0.2.1
Summary: Simple recipe to collect symbolic links in one directory.
Home-page: http://github.com/svetlyak40wt/svetlyak40wt.recipe.symlinks
Author: Alexander Artemenko
Author-email: svetlyak.40wt@gmail.com
License: New BSD License
Keywords: buildout recipe
Platform: UNKNOWN
Classifier: License :: OSI Approved :: BSD License
Classifier: Framework :: Buildout
Classifier: Programming Language :: Python
